sdelete/__init__.py
sdelete/cli.py
sdelete-0.1.2.dist-info/METADATA
sdelete-0.1.2.dist-info/WHEEL
sdelete-0.1.2.dist-info/entry_points.txt
sdelete-0.1.2.dist-info/top_level.txt
sdelete-0.1.2.dist-info/RECORD
