Metadata-Version: 2.4
Name: sdelete
Version: 0.1.2
Summary: Terminal-based secure file deletion tool with ncurses UI
Home-page: https://github.com/bearenbey/sdelete
Author: Eren Öğrül
Author-email: Eren Öğrül <termapp@pm.me>
License: MIT
Requires-Python: >=3.8
Dynamic: author
Dynamic: home-page
Dynamic: requires-python
